lrdbenchmark/__init__.py
lrdbenchmark/_version.py
lrdbenchmark/assets.py
lrdbenchmark/exceptions.py
lrdbenchmark/py.typed
lrdbenchmark/random_manager.py
lrdbenchmark/utils.py
lrdbenchmark/analysis/__init__.py
lrdbenchmark/analysis/adaptive_classical_estimators.py
lrdbenchmark/analysis/adaptive_estimator.py
lrdbenchmark/analysis/advanced_metrics.py
lrdbenchmark/analysis/backend_utils.py
lrdbenchmark/analysis/base_estimator.py
lrdbenchmark/analysis/calibration_utils.py
lrdbenchmark/analysis/comprehensive_adaptive_estimators.py
lrdbenchmark/analysis/diagnostics.py
lrdbenchmark/analysis/benchmark/__init__.py
lrdbenchmark/analysis/benchmark/engine.py
lrdbenchmark/analysis/high_performance/jax/__init__.py
lrdbenchmark/analysis/high_performance/jax/cwt_jax.py
lrdbenchmark/analysis/high_performance/jax/dfa_jax.py
lrdbenchmark/analysis/high_performance/jax/dma_jax.py
lrdbenchmark/analysis/high_performance/jax/gph_jax.py
lrdbenchmark/analysis/high_performance/jax/higuchi_jax.py
lrdbenchmark/analysis/high_performance/jax/mfdfa_jax.py
lrdbenchmark/analysis/high_performance/jax/multifractal_wavelet_leaders_jax.py
lrdbenchmark/analysis/high_performance/jax/periodogram_jax.py
lrdbenchmark/analysis/high_performance/jax/rs_jax.py
lrdbenchmark/analysis/high_performance/jax/wavelet_log_variance_jax.py
lrdbenchmark/analysis/high_performance/jax/wavelet_variance_jax.py
lrdbenchmark/analysis/high_performance/jax/wavelet_whittle_jax.py
lrdbenchmark/analysis/high_performance/jax/whittle_jax.py
lrdbenchmark/analysis/high_performance/numba/__init__.py
lrdbenchmark/analysis/high_performance/numba/cwt_numba.py
lrdbenchmark/analysis/high_performance/numba/dfa_numba.py
lrdbenchmark/analysis/high_performance/numba/dma_numba.py
lrdbenchmark/analysis/high_performance/numba/gph_numba.py
lrdbenchmark/analysis/high_performance/numba/higuchi_numba.py
lrdbenchmark/analysis/high_performance/numba/mfdfa_numba.py
lrdbenchmark/analysis/high_performance/numba/multifractal_wavelet_leaders_numba.py
lrdbenchmark-2.4.0.dist-info/licenses/LICENSE
lrdbenchmark-2.4.0.dist-info/METADATA
lrdbenchmark-2.4.0.dist-info/WHEEL
lrdbenchmark-2.4.0.dist-info/top_level.txt
lrdbenchmark-2.4.0.dist-info/RECORD
