Metadata-Version: 2.4
Name: lrdbenchmark
Version: 2.4.0
Summary: Comprehensive Long-Range Dependence Benchmarking Framework with 20 Estimators (13 Classical, 3 ML, 4 Neural Networks) + 5 Demonstration Notebooks
Author-email: "Davian R. Chin" <d.r.chin@reading.ac.uk>
License: MIT
Project-URL: Homepage, https://github.com/dave2k77/lrdbenchmark
Project-URL: Documentation, https://lrdbenchmark.readthedocs.io/
Project-URL: Repository, https://github.com/dave2k77/lrdbenchmark.git
Project-URL: Issues, https://github.com/dave2k77/lrdbenchmark/issues
Project-URL: Download, https://pypi.org/project/lrdbenchmark/
Project-URL: Source, https://github.com/dave2k77/lrdbenchmark
Project-URL: DOI, https://doi.org/10.5281/zenodo.17535020
Keywords: long-range dependence,hurst parameter,time series analysis,benchmarking,machine learning,neural networks,reproducible research,fractional brownian motion,wavelet analysis,spectral analysis
Classifier: Development Status :: 5 - Production/Stable
Classifier: Intended Audience :: Science/Research
Classifier: Intended Audience :: Developers
Classifier: License :: OSI Approved :: MIT License
Classifier: Operating System :: OS Independent
Classifier: Programming Language :: Python :: 3
Classifier: Programming Language :: Python :: 3.10
Classifier: Programming Language :: Python :: 3.11
Classifier: Programming Language :: Python :: 3.12
Classifier: Topic :: Scientific/Engineering :: Mathematics
Classifier: Topic :: Scientific/Engineering :: Physics
Classifier: Topic :: Scientific/Engineering :: Information Analysis
Classifier: Topic :: Software Development :: Libraries :: Python Modules
Classifier: Topic :: Scientific/Engineering :: Artificial Intelligence
Requires-Python: <3.13,>=3.10
License-File: LICENSE
Requires-Dist: numpy>=1.26.0
Requires-Dist: scipy>=1.10.0
Requires-Dist: scikit-learn>=1.2.0
Requires-Dist: pandas>=1.5.0
Requires-Dist: pywavelets>=1.3.0
Requires-Dist: matplotlib>=3.5.0
Requires-Dist: seaborn>=0.11.0
Requires-Dist: psutil>=5.8.0
Requires-Dist: networkx>=2.6.0
Requires-Dist: joblib>=1.1.0
Provides-Extra: dev
Requires-Dist: pytest>=6.0; extra == "dev"
Requires-Dist: pytest-cov>=2.12; extra == "dev"
Requires-Dist: black>=21.0; extra == "dev"
Requires-Dist: flake8>=3.9; extra == "dev"
Requires-Dist: mypy>=0.910; extra == "dev"
Provides-Extra: docs
Requires-Dist: sphinx>=4.0; extra == "docs"
Requires-Dist: sphinx-rtd-theme>=0.5; extra == "docs"
Requires-Dist: myst-parser>=0.15; extra == "docs"
Provides-Extra: dashboard
Requires-Dist: streamlit>=1.28.0; extra == "dashboard"
Requires-Dist: plotly>=5.15.0; extra == "dashboard"
Provides-Extra: accel-jax
Requires-Dist: jax>=0.4.28; extra == "accel-jax"
Requires-Dist: jaxlib>=0.4.28; extra == "accel-jax"
Provides-Extra: accel-pytorch
Requires-Dist: torch>=2.2.0; extra == "accel-pytorch"
Provides-Extra: accel-numba
Requires-Dist: numba>=0.60.0; extra == "accel-numba"
Provides-Extra: accel-all
Requires-Dist: jax>=0.4.28; extra == "accel-all"
Requires-Dist: jaxlib>=0.4.28; extra == "accel-all"
Requires-Dist: torch>=2.2.0; extra == "accel-all"
Requires-Dist: numba>=0.60.0; extra == "accel-all"
Provides-Extra: bayes
Requires-Dist: optuna>=3.0.0; extra == "bayes"
Requires-Dist: numpyro>=0.12.0; extra == "bayes"
Dynamic: license-file
